knit2pdf/__init__.py
knit2pdf/cli.py
knit2pdf/config/knit2pdfoptions.py
knit2pdf/config/openai.py
knit2pdf/knit2pdf.py
knit2pdf-0.1.0.dist-info/METADATA
knit2pdf-0.1.0.dist-info/WHEEL
knit2pdf-0.1.0.dist-info/entry_points.txt
knit2pdf-0.1.0.dist-info/RECORD
