Metadata-Version: 2.3
Name: knit2pdf
Version: 0.1.0
Summary: Creates a knitting and/or crochet pattern from a youtube video
Author: Sara Soh
Author-email: sara.soh.ql@gmail.com
Requires-Python: >=3.9
Classifier: Programming Language :: Python :: 3
Classifier: Programming Language :: Python :: 3.9
Classifier: Programming Language :: Python :: 3.10
Classifier: Programming Language :: Python :: 3.11
Classifier: Programming Language :: Python :: 3.12
Requires-Dist: click (>=8.1.8,<9.0.0)
Requires-Dist: onnxruntime (>=1.15.1)
Requires-Dist: openai (>=1.59.6,<2.0.0)
Requires-Dist: pydantic (>=2.10.5,<3.0.0)
Requires-Dist: torch (>=2.5.1,<3.0.0)
Requires-Dist: whisperx (>=3.3.1,<4.0.0)
Requires-Dist: wkhtmltopdf (>=0.2,<0.3)
Requires-Dist: youtube-dl (==2021.12.17)
